spi_lora/LoRa.py
spi_lora/LoRaArgumentParser.py
spi_lora/__init__.py
spi_lora/board_config.py
spi_lora/constants.py
spi_lora-0.2.1.dist-info/LICENSE
spi_lora-0.2.1.dist-info/METADATA
spi_lora-0.2.1.dist-info/WHEEL
spi_lora-0.2.1.dist-info/top_level.txt
spi_lora-0.2.1.dist-info/RECORD
